mitcf/__init__.py
mitcf/mitcf.py
mitcf/pg_logger.py
mitcf-1.0.1.dist-info/METADATA
mitcf-1.0.1.dist-info/WHEEL
mitcf-1.0.1.dist-info/top_level.txt
mitcf-1.0.1.dist-info/RECORD
