Metadata-Version: 2.1
Name: mitcf
Version: 1.0.1
Summary: Log to Postgres DB
Home-page: https://github.com/...
Author: Florian Metzler
Author-email: fmetzler@mit.edu
License: MIT
Platform: UNKNOWN
Requires-Dist: psycopg2
Requires-Dist: numpy
